bread_messenger_client-0.1.data/scripts/client_run
client/__init__.py
client/client_main.py
client/client/__init__.py
client/client/add_contact.py
client/client/client_database.py
client/client/client_transport.py
client/client/del_contact.py
client/client/main_window.py
client/client/main_window_conv.py
client/client/start_dialog.py
client/common/__init__.py
client/common/decorators.py
client/common/descriptors.py
client/common/errors.py
client/common/metaclasses.py
client/common/utils.py
client/common/variables.py
client/logs/__init__.py
client/logs/config_client_log.py
client/unit_test/__init__.py
bread_messenger_client-0.1.dist-info/METADATA
bread_messenger_client-0.1.dist-info/WHEEL
bread_messenger_client-0.1.dist-info/top_level.txt
bread_messenger_client-0.1.dist-info/RECORD
